_utils/__init__.py
_utils/apps.py
_utils/models.py
ds/__init__.py
ds/apps.py
ds/models.py
rp/__init__.py
rp/admin.py
rp/apps.py
rp/models.py
rp/migrations/0001_initial.py
rp/migrations/0002_auto_20220707_1025.py
rp/migrations/__init__.py
rxn/__init__.py
rxn/admin.py
rxn/apps.py
rxn/models.py
rxn/migrations/0001_initial.py
rxn/migrations/0002_reaction_latex.py
rxn/migrations/0003_reaction_ordered_text.py
rxn/migrations/__init__.py
django_valem-0.1.14.dist-info/LICENSE
django_valem-0.1.14.dist-info/METADATA
django_valem-0.1.14.dist-info/WHEEL
django_valem-0.1.14.dist-info/top_level.txt
django_valem-0.1.14.dist-info/RECORD
