Metadata-Version: 2.1
Name: django-valem
Version: 0.1.14
Summary: A collection of Django apps defining data models for managing chemical species, reactions and datasets.
Home-page: https://github.com/xnx/django-valem
Author: Christian Hill
Author-email: ch.hill@iaea.org
Project-URL: Bug Reports, https://github.com/xnx/django-valem/issues
Keywords: django,chemistry,formula,species,state,reaction
Classifier: Development Status :: 3 - Alpha
Classifier: Intended Audience :: Science/Research
Classifier: Topic :: Scientific/Engineering :: Chemistry
Classifier: Topic :: Scientific/Engineering :: Physics
Classifier: License :: OSI Approved :: Apache Software License
Classifier: Programming Language :: Python :: 3
Classifier: Programming Language :: Python :: 3.6
Classifier: Programming Language :: Python :: 3.7
Classifier: Programming Language :: Python :: 3.8
Classifier: Programming Language :: Python :: 3.9
Classifier: Programming Language :: Python :: 3.10
Classifier: Programming Language :: Python :: 3.11
Classifier: Programming Language :: Python :: 3 :: Only
Classifier: Framework :: Django
Classifier: Operating System :: OS Independent
Requires-Python: >=3.6
License-File: LICENSE
Requires-Dist: pyvalem >=2.5.9
Requires-Dist: django-pyref >=0.5.1
Provides-Extra: dev
Requires-Dist: black ; extra == 'dev'
Requires-Dist: coverage ; extra == 'dev'
Requires-Dist: django ==3 ; extra == 'dev'
Requires-Dist: ipython ; extra == 'dev'
